{
    "name": "News Widget",
    "class": "c-news-widget",
    "version": "1.0.0",
    "creator": {
        "name": "Alex Foxleigh",
        "github_username": "foxleigh81"
    },
    "description": "A widget for all news items",
    "standard_or_universal": "standard",
    "parents": "",
    "children": "c-news-list, c-featured-news-list",
    "notes": {
        "backend": "",
        "frontend": ""
    },
    "backend_classes": {},
    "has_js": false,
    "integrated": false,
    "is_working": false,
    "screenshot": "https://lh3.googleusercontent.com/Qy9vZwE21KJiCjuNan9PfGGMgFoAdHAij_t4tlFojiBa0rp_ZjYvez_E80PAycq9AtY7ot2sh_VeOj0=w2572-h1428-rw",
    "example_link": "http://intranet.justice.gov.uk",
    "changelog": [{
        "date": "02/02/17",
        "author": "Alex Foxleigh",
        "description": "Created component"
    }]
}